functionTime/__init__.py
functionTime/app.py
functionTime-0.0.6.dist-info/METADATA
functionTime-0.0.6.dist-info/WHEEL
functionTime-0.0.6.dist-info/top_level.txt
functionTime-0.0.6.dist-info/RECORD
