Metadata-Version: 2.1
Name: functionTime
Version: 0.0.6
Summary: Time your function
Author: Nayan-Chimariya
Author-email: <cnayan789@gmail.com>
Classifier: Programming Language :: Python :: 3
Classifier: Operating System :: Unix
Classifier: Operating System :: MacOS :: MacOS X
Classifier: Operating System :: Microsoft :: Windows
Requires-Dist: colorama
